MANIFEST.in
README.rst
setup.py
django_paging.egg-info/PKG-INFO
django_paging.egg-info/SOURCES.txt
django_paging.egg-info/dependency_links.txt
django_paging.egg-info/requires.txt
django_paging.egg-info/top_level.txt
paging/__init__.py
paging/helpers.py
paging/models.py
paging/paginators.py
paging/tests.py
paging/templates/.DS_Store
paging/templates/paging/pager.html
paging/templatetags/__init__.py
paging/templatetags/paging_extras.py